PyBondLab/FilterClass.py
PyBondLab/PyBondLab.py
PyBondLab/StrategyClass.py
PyBondLab/__init__.py
PyBondLab/data/__init__.py
PyBondLab/data/data_loading.py
PyBondLab/data/WRDS/__init__.py
PyBondLab/data/WRDS/breakpoints_wrds.csv
PyBondLab/iotools/PyBondLabResults.py
PyBondLab/iotools/__init__.py
PyBondLab/iotools/table.py
PyBondLab-0.1.5.dist-info/LICENSE
PyBondLab-0.1.5.dist-info/METADATA
PyBondLab-0.1.5.dist-info/WHEEL
PyBondLab-0.1.5.dist-info/top_level.txt
PyBondLab-0.1.5.dist-info/RECORD
