Metadata-Version: 2.1
Name: PyBondLab
Version: 0.1.5
Summary: Performs portfolio sorting and strategy evaluation for corporate bonds
Home-page: https://github.com/GiulioRossetti94/PyBondLab
Author: Giulio Rossetti, Alex Dickerson
Author-email: Giulio.Rossetti.1@wbs.ac.uk, alexander.dickerson1@unsw.edu.au
License: MIT
Project-URL: Open Source Bond Asset Pricing, https://openbondassetpricing.com/
Project-URL: Source Code, https://github.com/GiulioRossetti94/PyBondLab
Project-URL: Bug Tracker, https://github.com/GiulioRossetti94/PyBondLab/issues
Keywords: corporate bonds,portfolio sorting,data cleaning
Requires-Python: >=3.11
License-File: LICENSE
Requires-Dist: numpy
Requires-Dist: pandas
Requires-Dist: statsmodels
Requires-Dist: matplotlib
